xmllayout2/__init__.py
xmllayout2/formatters.py
xmllayout2/handlers.py
xmllayout2/tests/__init__.py
xmllayout2/tests/test_formatters.py
xmllayout2-2.0.2.dist-info/LICENSE
xmllayout2-2.0.2.dist-info/METADATA
xmllayout2-2.0.2.dist-info/WHEEL
xmllayout2-2.0.2.dist-info/top_level.txt
xmllayout2-2.0.2.dist-info/RECORD
