Metadata-Version: 2.2
Name: xmllayout2
Version: 2.0.2
Summary: Formats Python log messages as log4j XMLLayout XML
Home-page: http://pypi.python.org/pypi/XMLLayout
Author: Jonas Lindner
Author-email: jonaslindner55@gmail.com
License: BSD
Keywords: logging log4j
Classifier: Development Status :: 5 - Production/Stable
Classifier: Intended Audience :: Developers
Classifier: License :: OSI Approved :: BSD License
Classifier: Programming Language :: Python
Classifier: Programming Language :: Python :: 3
Classifier: Programming Language :: Python :: Implementation :: CPython
Classifier: Programming Language :: Python :: Implementation :: PyPy
Classifier: Programming Language :: Python :: Implementation :: Jython
Classifier: Topic :: System :: Logging
License-File: LICENSE
Provides-Extra: test
Requires-Dist: pytest>=6.2.2; extra == "test"
Dynamic: author
Dynamic: author-email
Dynamic: classifier
Dynamic: description
Dynamic: home-page
Dynamic: keywords
Dynamic: license
Dynamic: summary
